pycuties/__init__.py
pycuties/expandobox.py
pycuties/icons.py
pycuties/__pycache__/__init__.cpython-39.pyc
pycuties/__pycache__/expandobox.cpython-39.pyc
pycuties/__pycache__/icons.cpython-39.pyc
pycuties/__pycache__/svg.cpython-39.pyc
pycuties-0.1.0.dist-info/METADATA
pycuties-0.1.0.dist-info/WHEEL
pycuties-0.1.0.dist-info/top_level.txt
pycuties-0.1.0.dist-info/RECORD
